{
  "version": "1.0.0",
  "lastUpdated": "2025-01-06T00:00:00Z",
  "media": [
    {
      "filename": "animal-chat.gif",
      "path": "https://raw.githubusercontent.com/6b6t/6b6t-embeds/main/animal-chat.gif",
      "type": "image/gif",
      "size": 1024000,
      "category": "animations",
      "description": "Animal chat animated GIF"
    },
    {
      "filename": "language-and-roles.gif",
      "path": "https://raw.githubusercontent.com/6b6t/6b6t-embeds/main/language-and-roles.gif",
      "type": "image/gif",
      "size": 1024000,
      "category": "discord",
      "description": "6b6t Discord #language-and-roles channel GIF"
    }
  ]
}
